[
  {
    "id": "skeleton_warrior",
    "name": "Skeleton Warrior",
    "hp": 80,
    "armor": 5,
    "attackDamage": 12,
    "attackSpeed": 1,
    "resistances": {
      "fire": 0,
      "ice": 0,
      "lightning": 0,
      "physical": 0,
      "poison": 20
    },
    "xpReward": 15
  },
  {
    "id": "fire_imp",
    "name": "Fire Imp",
    "hp": 50,
    "armor": 2,
    "attackDamage": 18,
    "attackSpeed": 1.5,
    "resistances": {
      "fire": 50,
      "ice": -20,
      "lightning": 0,
      "physical": 0,
      "poison": 0
    },
    "xpReward": 20,
    "onHitStatus": "burn"
  },
  {
    "id": "ice_golem",
    "name": "Ice Golem",
    "hp": 150,
    "armor": 20,
    "attackDamage": 20,
    "attackSpeed": 0.7,
    "resistances": {
      "fire": -30,
      "ice": 60,
      "lightning": 0,
      "physical": 10,
      "poison": 0
    },
    "xpReward": 35,
    "onHitStatus": "chill"
  },
  {
    "id": "corrupted_mage",
    "name": "Corrupted Mage",
    "hp": 60,
    "armor": 0,
    "attackDamage": 30,
    "attackSpeed": 0.8,
    "resistances": {
      "fire": 10,
      "ice": 10,
      "lightning": 10,
      "physical": -10,
      "poison": 0
    },
    "xpReward": 25
  },
  {
    "id": "plague_rat",
    "name": "Plague Rat",
    "hp": 30,
    "armor": 0,
    "attackDamage": 8,
    "attackSpeed": 2,
    "resistances": {
      "fire": 0,
      "ice": 0,
      "lightning": 0,
      "physical": 0,
      "poison": 40
    },
    "xpReward": 10,
    "onHitStatus": "poison"
  },
  {
    "id": "thunder_beast",
    "name": "Thunder Beast",
    "hp": 120,
    "armor": 10,
    "attackDamage": 25,
    "attackSpeed": 1,
    "resistances": {
      "fire": 0,
      "ice": 0,
      "lightning": 50,
      "physical": 0,
      "poison": 0
    },
    "xpReward": 30,
    "onHitStatus": "shock"
  },
  {
    "id": "bone_archer",
    "name": "Bone Archer",
    "hp": 55,
    "armor": 3,
    "attackDamage": 22,
    "attackSpeed": 1.2,
    "resistances": {
      "fire": 0,
      "ice": 0,
      "lightning": 0,
      "physical": 0,
      "poison": 10
    },
    "xpReward": 18
  },
  {
    "id": "shadow_wraith",
    "name": "Shadow Wraith",
    "hp": 70,
    "armor": 0,
    "attackDamage": 28,
    "attackSpeed": 1.3,
    "resistances": {
      "fire": 10,
      "ice": 10,
      "lightning": 10,
      "physical": 30,
      "poison": 10
    },
    "xpReward": 28
  },
  {
    "id": "venom_spider",
    "name": "Venom Spider",
    "hp": 45,
    "armor": 2,
    "attackDamage": 15,
    "attackSpeed": 1.8,
    "resistances": {
      "fire": 0,
      "ice": 0,
      "lightning": 0,
      "physical": 0,
      "poison": 60
    },
    "xpReward": 22,
    "onHitStatus": "poison"
  },
  {
    "id": "stone_guardian",
    "name": "Stone Guardian",
    "hp": 200,
    "armor": 30,
    "attackDamage": 35,
    "attackSpeed": 0.5,
    "resistances": {
      "fire": 0,
      "ice": 20,
      "lightning": 0,
      "physical": 20,
      "poison": 30
    },
    "xpReward": 50
  },
  {
    "id": "blood_fiend",
    "name": "Blood Fiend",
    "hp": 90,
    "armor": 5,
    "attackDamage": 32,
    "attackSpeed": 1.1,
    "resistances": {
      "fire": 0,
      "ice": 0,
      "lightning": 0,
      "physical": -10,
      "poison": 0
    },
    "xpReward": 32,
    "onHitStatus": "bleed"
  },
  {
    "id": "frost_specter",
    "name": "Frost Specter",
    "hp": 75,
    "armor": 0,
    "attackDamage": 24,
    "attackSpeed": 1.4,
    "resistances": {
      "fire": -20,
      "ice": 70,
      "lightning": 0,
      "physical": 20,
      "poison": 0
    },
    "xpReward": 26,
    "onHitStatus": "chill"
  },
  {
    "id": "inferno_golem",
    "name": "Inferno Golem",
    "hp": 180,
    "armor": 25,
    "attackDamage": 30,
    "attackSpeed": 0.6,
    "resistances": {
      "fire": 80,
      "ice": -40,
      "lightning": 0,
      "physical": 15,
      "poison": 0
    },
    "xpReward": 45,
    "onHitStatus": "burn"
  },
  {
    "id": "elite_champion",
    "name": "Elite Champion",
    "hp": 300,
    "armor": 40,
    "attackDamage": 45,
    "attackSpeed": 0.9,
    "resistances": {
      "fire": 20,
      "ice": 20,
      "lightning": 20,
      "physical": 20,
      "poison": 20
    },
    "xpReward": 80,
    "isElite": true,
    "mechanic": "enrage"
  },
  {
    "id": "void_herald",
    "name": "Void Herald",
    "hp": 130,
    "armor": 10,
    "attackDamage": 38,
    "attackSpeed": 1,
    "resistances": {
      "fire": 10,
      "ice": 10,
      "lightning": 10,
      "physical": 0,
      "poison": 10,
      "chaos": 50
    },
    "xpReward": 55,
    "isElite": true
  }
]
